CHANGES.txt
LICENSE.txt
MANIFEST.in
README.txt
TODO.txt
bootstrap.py
setup.py
src/p01/__init__.py
src/p01.remote.egg-info/PKG-INFO
src/p01.remote.egg-info/SOURCES.txt
src/p01.remote.egg-info/dependency_links.txt
src/p01.remote.egg-info/namespace_packages.txt
src/p01.remote.egg-info/not-zip-safe
src/p01.remote.egg-info/requires.txt
src/p01.remote.egg-info/top_level.txt
src/p01/remote/README.txt
src/p01/remote/__init__.py
src/p01/remote/configure.zcml
src/p01/remote/exceptions.py
src/p01/remote/interfaces.py
src/p01/remote/job.py
src/p01/remote/layer.py
src/p01/remote/layer.zcml
src/p01/remote/namespace.py
src/p01/remote/namespace.zcml
src/p01/remote/processor.py
src/p01/remote/publisher.py
src/p01/remote/scheduler.py
src/p01/remote/scheduler.txt
src/p01/remote/subscriber.py
src/p01/remote/subscriber.zcml
src/p01/remote/testing.py
src/p01/remote/tests.py
src/p01/remote/vocabulary.py
src/p01/remote/vocabulary.zcml
src/p01/remote/worker.py
src/p01/remote/worker.txt
src/p01/remote/browser/__init__.py
src/p01/remote/browser/configure.zcml
src/p01/remote/browser/job.py
src/p01/remote/browser/job.zcml
src/p01/remote/browser/jobs.pt
src/p01/remote/browser/processor.pt
src/p01/remote/browser/processor.py
src/p01/remote/browser/processor.zcml
src/p01/remote/browser/scheduler.pt
src/p01/remote/browser/scheduler.py
src/p01/remote/browser/scheduler.zcml
src/p01/remote/generations/__init__.py
src/p01/remote/generations/configure.zcml